Server_3_free_threads/__init__.py
Server_3_free_threads/__main__.py
Server_3_free_threads/classes/__init__.py
Server_3_free_threads/classes/additional_class.py
Server_3_free_threads/classes/base_class.py
Server_3_free_threads/classes/response_headers_class.py
Server_3_free_threads/classes/server_actions_class.py
Server_3_free_threads/initial_func.py
Server_3_free_threads/parsers/__init__.py
Server_3_free_threads/parsers/base.py
Server_3_free_threads/parsers/parser_args.py
Server_3_free_threads/parsers/parser_config.py
server_3_free_threads-0.2.19.dist-info/METADATA
server_3_free_threads-0.2.19.dist-info/WHEEL
server_3_free_threads-0.2.19.dist-info/RECORD
