Metadata-Version: 2.3
Name: Server_3_free_threads
Version: 0.2.19
Summary: WSGI server based on threads
License: MIT
Keywords: server,WSGI,wsgi
Author: Vadim Kazakov
Author-email: skolkovoinovations@gmail.com
Requires-Python: >=3.10.0
Classifier: Programming Language :: Python :: 3.11
Classifier: License :: OSI Approved :: MIT License
Classifier: Operating System :: POSIX :: Linux
